<?xml version="1.0" encoding="UTF-8"?>
<!DOCTYPE ode SYSTEM "content.dtd">
<ode xmlns="http://www.intef.es/xsd/ode" version="2.0">
<userPreferences>
  <userPreference>
    <key>theme</key>
    <value>base</value>
  </userPreference>
</userPreferences>
<odeResources>
  <odeResource>
    <key>odeId</key>
    <value>20260419183926G9IDWY</value>
  </odeResource>
  <odeResource>
    <key>odeVersionId</key>
    <value>202604191839266UF07G</value>
  </odeResource>
  <odeResource>
    <key>exe_version</key>
    <value>3.0</value>
  </odeResource>
</odeResources>
<odeProperties>
  <odeProperty>
    <key>pp_title</key>
    <value>Into the unknown</value>
  </odeProperty>
  <odeProperty>
    <key>pp_subtitle</key>
    <value>Situación de aprendizaje. B2 CDD. </value>
  </odeProperty>
  <odeProperty>
    <key>pp_author</key>
    <value>Paula Castillo Martín</value>
  </odeProperty>
  <odeProperty>
    <key>pp_description</key>
    <value>Este producto está hecho para el curso de B2 de CDD. Es una situación de aprendizaje para el primer ciclo de la ESO.</value>
  </odeProperty>
  <odeProperty>
    <key>pp_lang</key>
    <value>es</value>
  </odeProperty>
  <odeProperty>
    <key>pp_license</key>
    <value>creative commons: attribution - share alike 4.0</value>
  </odeProperty>
  <odeProperty>
    <key>pp_licenseUrl</key>
    <value>https://creativecommons.org/licenses/by-sa/4.0/</value>
  </odeProperty>
  <odeProperty>
    <key>pp_theme</key>
    <value>base</value>
  </odeProperty>
  <odeProperty>
    <key>pp_exelearning_version</key>
    <value>v4.0.0-rc1</value>
  </odeProperty>
  <odeProperty>
    <key>pp_modified</key>
    <value>1776616630713</value>
  </odeProperty>
  <odeProperty>
    <key>pp_addExeLink</key>
    <value>true</value>
  </odeProperty>
  <odeProperty>
    <key>pp_addPagination</key>
    <value>false</value>
  </odeProperty>
  <odeProperty>
    <key>pp_addSearchBox</key>
    <value>false</value>
  </odeProperty>
  <odeProperty>
    <key>pp_addAccessibilityToolbar</key>
    <value>false</value>
  </odeProperty>
  <odeProperty>
    <key>pp_addMathJax</key>
    <value>false</value>
  </odeProperty>
  <odeProperty>
    <key>exportSource</key>
    <value>true</value>
  </odeProperty>
  <odeProperty>
    <key>pp_globalFont</key>
    <value>default</value>
  </odeProperty>
</odeProperties>
<odeNavStructures>
<odeNavStructure>
  <odePageId>page-1776612272008-8j793dnil</odePageId>
  <odeParentPageId></odeParentPageId>
  <pageName>Presentación y descripción del proyecto</pageName>
  <odeNavStructureOrder>1</odeNavStructureOrder>
  <odeNavStructureProperties>
    <odeNavStructureProperty>
      <key>titlePage</key>
      <value>Presentación y descripción del proyecto</value>
    </odeNavStructureProperty>
  </odeNavStructureProperties>
  <odePagStructures>
    <odePagStructure>
      <odePageId>page-1776612272008-8j793dnil</odePageId>
      <odeBlockId>block-1776612289040-hgx44xni6</odeBlockId>
      <blockName>Texto</blockName>
      <iconName></iconName>
      <odePagStructureOrder>1</odePagStructureOrder>
      <odePagStructureProperties>
        <odePagStructureProperty>
          <key>visibility</key>
          <value>true</value>
        </odePagStructureProperty>
        <odePagStructureProperty>
          <key>teacherOnly</key>
          <value>false</value>
        </odePagStructureProperty>
        <odePagStructureProperty>
          <key>allowToggle</key>
          <value>true</value>
        </odePagStructureProperty>
        <odePagStructureProperty>
          <key>minimized</key>
          <value>false</value>
        </odePagStructureProperty>
        <odePagStructureProperty>
          <key>cssClass</key>
          <value></value>
        </odePagStructureProperty>
      </odePagStructureProperties>
      <odeComponents>
        <odeComponent>
          <odePageId>page-1776612272008-8j793dnil</odePageId>
          <odeBlockId>block-1776612289040-hgx44xni6</odeBlockId>
          <odeIdeviceId>idevice-1776612289032-dshxoo58l</odeIdeviceId>
          <odeIdeviceTypeName>text</odeIdeviceTypeName>
          <htmlView><![CDATA[<div class="exe-text-template">
    <p style="text-align: center;"><strong>SITUACIÓN DE APRENDIZAJE: INTO THE UNKNOWN</strong></p>
<p style="text-align: justify;"><strong>Temporalización:</strong> Se desarrollará durante el segundo trimestre, concretamente en el mes de febrero.<br /><strong>Centro de interés:</strong> El eje principal de esta situación de aprendizaje se articula en torno a la pregunta: ¿Dónde vamos? A partir de ella, el alumnado explorará la cultura y la historia de distintos países angloparlantes, estableciendo comparaciones con su propio contexto cultural.<br /><strong>Nivel</strong>: 1º ESO o 2º ESO<br /><strong>Idioma</strong>: Inglés<br /><strong>Materias implicadas: </strong>Principalmente Inglés como Primera Lengua Extranjera, con conexiones interdisciplinares con Geografía e Historia, Valores y Matemáticas.<br /><strong></strong></p>
<p style="text-align: justify;"><strong>¿Qué va a aprender el alumno?</strong><br />Esta situación de aprendizaje se ha diseñado teniendo en cuenta lo establecido en los artículos 4, 5 y 6 del Decreto 102/2023. A través de ella, el alumnado trabajará la comprensión de cómo el contexto histórico influye en la sociedad y en la identidad cultural de los países (letra J), así como el reconocimiento de la influencia de la historia en el patrimonio cultural andaluz (letra N).</p>
<p style="text-align: justify;">Además, se fomentará el uso del inglés como herramienta de comunicación en contextos reales, promoviendo el trabajo cooperativo. El alumnado se acercará a diferentes formas de vida, desarrollando una actitud de respeto y valoración tanto hacia otras culturas como hacia la propia.</p>
<p style="text-align: center;"><strong>Justificación</strong></p>
<p style="text-align: justify;">La elección de esta situación de aprendizaje viene de las conclusiones a las que llegué en la actividad del principio de curso con la rutina de pensamiento. Me di cuenta de que al alumnado le cuesta bastante adaptarse a metodologías más activas, sobre todo cuando están acostumbrados a clases más tradicionales.</p>
<p>Por eso, he decidido hacerlo en 1º de ESO, porque creo que es un buen momento para que empiecen a trabajar de otra manera desde el principio y no les pille de nuevas más adelante.</p>
<p>También, a partir de lo que me he aprendido de otras experiencias, he intentado organizarme mejor para evitar esos pequeños momentos de caos. Voy a usar listas de cotejo para ser más eficaz a la hora de evaluar, y también mezclaré actividades que ya sé que funcionan con otras más nuevas, además de usar recursos audiovisuales y Moodle para hacerlo un poco más dinámico.</p>
<p>Otra cosa que quiero cuidar más es cómo se sienten ellos. Muchas veces les cuesta participar en inglés por vergüenza o miedo a equivocarse, así que la idea es que el ambiente sea lo más cómodo posible, que no tengan esa sensación de estar siendo juzgados todo el rato.</p>
<p>En cuanto a la evaluación, no quiero que sea solo cosa mía. Me interesa que ellos también participen, así que habrá momentos de autoevaluación y de evaluación entre compañeros, para que tomen un poco de conciencia de cómo están trabajando.</p>
<p>Y al terminar, quiero dejar un momento de reflexión propia para ver qué ha pasado realmente. Compararé los resultados con los de otros años, cuando he trabajado de forma más tradicional, para ver si esto funciona mejor, igual o peor para saber si debo seguir por este camino de trabajo o si hay cosas que tengo que cambiar.<br /></p>
</div>]]></htmlView>
          <jsonProperties><![CDATA[{"ideviceId":"idevice-1776612289032-dshxoo58l","textInfoDurationInput":"","textInfoDurationTextInput":"Duración","textInfoParticipantsInput":"","textInfoParticipantsTextInput":"Agrupamiento","textTextarea":"<p style=\"text-align: center;\"><strong>SITUACIÓN DE APRENDIZAJE: INTO THE UNKNOWN</strong></p>\n<p style=\"text-align: justify;\"><strong>Temporalización:</strong> Se desarrollará durante el segundo trimestre, concretamente en el mes de febrero.<br /><strong>Centro de interés:</strong> El eje principal de esta situación de aprendizaje se articula en torno a la pregunta: ¿Dónde vamos? A partir de ella, el alumnado explorará la cultura y la historia de distintos países angloparlantes, estableciendo comparaciones con su propio contexto cultural.<br /><strong>Nivel</strong>: 1º ESO o 2º ESO<br /><strong>Idioma</strong>: Inglés<br /><strong>Materias implicadas: </strong>Principalmente Inglés como Primera Lengua Extranjera, con conexiones interdisciplinares con Geografía e Historia, Valores y Matemáticas.<br /><strong></strong></p>\n<p style=\"text-align: justify;\"><strong>¿Qué va a aprender el alumno?</strong><br />Esta situación de aprendizaje se ha diseñado teniendo en cuenta lo establecido en los artículos 4, 5 y 6 del Decreto 102/2023. A través de ella, el alumnado trabajará la comprensión de cómo el contexto histórico influye en la sociedad y en la identidad cultural de los países (letra J), así como el reconocimiento de la influencia de la historia en el patrimonio cultural andaluz (letra N).</p>\n<p style=\"text-align: justify;\">Además, se fomentará el uso del inglés como herramienta de comunicación en contextos reales, promoviendo el trabajo cooperativo. El alumnado se acercará a diferentes formas de vida, desarrollando una actitud de respeto y valoración tanto hacia otras culturas como hacia la propia.</p>\n<p style=\"text-align: center;\"><strong>Justificación</strong></p>\n<p style=\"text-align: justify;\">La elección de esta situación de aprendizaje viene de las conclusiones a las que llegué en la actividad del principio de curso con la rutina de pensamiento. Me di cuenta de que al alumnado le cuesta bastante adaptarse a metodologías más activas, sobre todo cuando están acostumbrados a clases más tradicionales.</p>\n<p>Por eso, he decidido hacerlo en 1º de ESO, porque creo que es un buen momento para que empiecen a trabajar de otra manera desde el principio y no les pille de nuevas más adelante.</p>\n<p>También, a partir de lo que me he aprendido de otras experiencias, he intentado organizarme mejor para evitar esos pequeños momentos de caos. Voy a usar listas de cotejo para ser más eficaz a la hora de evaluar, y también mezclaré actividades que ya sé que funcionan con otras más nuevas, además de usar recursos audiovisuales y Moodle para hacerlo un poco más dinámico.</p>\n<p>Otra cosa que quiero cuidar más es cómo se sienten ellos. Muchas veces les cuesta participar en inglés por vergüenza o miedo a equivocarse, así que la idea es que el ambiente sea lo más cómodo posible, que no tengan esa sensación de estar siendo juzgados todo el rato.</p>\n<p>En cuanto a la evaluación, no quiero que sea solo cosa mía. Me interesa que ellos también participen, así que habrá momentos de autoevaluación y de evaluación entre compañeros, para que tomen un poco de conciencia de cómo están trabajando.</p>\n<p>Y al terminar, quiero dejar un momento de reflexión propia para ver qué ha pasado realmente. Compararé los resultados con los de otros años, cuando he trabajado de forma más tradicional, para ver si esto funciona mejor, igual o peor para saber si debo seguir por este camino de trabajo o si hay cosas que tengo que cambiar.<br /></p>","textFeedbackInput":"Mostrar retroalimentación","textFeedbackTextarea":""}]]></jsonProperties>
          <odeComponentsOrder>0</odeComponentsOrder>
          <odeComponentsProperties>
          </odeComponentsProperties>
        </odeComponent>
      </odeComponents>
    </odePagStructure>
  </odePagStructures>
</odeNavStructure>
<odeNavStructure>
  <odePageId>page-1776614654392-w4bv5niim</odePageId>
  <odeParentPageId></odeParentPageId>
  <pageName>Guía didáctica</pageName>
  <odeNavStructureOrder>2</odeNavStructureOrder>
  <odeNavStructureProperties>
    <odeNavStructureProperty>
      <key>titlePage</key>
      <value>Guía didáctica</value>
    </odeNavStructureProperty>
  </odeNavStructureProperties>
  <odePagStructures>
    <odePagStructure>
      <odePageId>page-1776614654392-w4bv5niim</odePageId>
      <odeBlockId>block-1776614748520-ueaavd9ts</odeBlockId>
      <blockName>Criterios de evaluación de cada actividad</blockName>
      <iconName></iconName>
      <odePagStructureOrder>1</odePagStructureOrder>
      <odePagStructureProperties>
        <odePagStructureProperty>
          <key>visibility</key>
          <value>true</value>
        </odePagStructureProperty>
        <odePagStructureProperty>
          <key>teacherOnly</key>
          <value>false</value>
        </odePagStructureProperty>
        <odePagStructureProperty>
          <key>allowToggle</key>
          <value>true</value>
        </odePagStructureProperty>
        <odePagStructureProperty>
          <key>minimized</key>
          <value>false</value>
        </odePagStructureProperty>
        <odePagStructureProperty>
          <key>cssClass</key>
          <value></value>
        </odePagStructureProperty>
      </odePagStructureProperties>
      <odeComponents>
        <odeComponent>
          <odePageId>page-1776614654392-w4bv5niim</odePageId>
          <odeBlockId>block-1776614748520-ueaavd9ts</odeBlockId>
          <odeIdeviceId>idevice-1776614748518-xb31p50vt</odeIdeviceId>
          <odeIdeviceTypeName>external-website</odeIdeviceTypeName>
          <htmlView><![CDATA[      <div id="iframeWebsiteIdevice">       <iframe src="https://docs.google.com/document/d/1j8Jy7WZNWgBqTOjVMtLlCe33wopdA8a0uiSJ7peyEEI/edit?usp=sharing" size="2" width="600" height="300" style="width:100%;">      </iframe>      <div class="iframe-error-message" style="display:none;">No se puede mostrar un iframe en HTTP en una web HTTPS.</div>       </div>      ]]></htmlView>
          <jsonProperties></jsonProperties>
          <odeComponentsOrder>0</odeComponentsOrder>
          <odeComponentsProperties>
          </odeComponentsProperties>
        </odeComponent>
      </odeComponents>
    </odePagStructure>
  </odePagStructures>
</odeNavStructure>
<odeNavStructure>
  <odePageId>page-1776612740113-wrve62d05</odePageId>
  <odeParentPageId></odeParentPageId>
  <pageName>Producto final: descripción y material</pageName>
  <odeNavStructureOrder>3</odeNavStructureOrder>
  <odeNavStructureProperties>
    <odeNavStructureProperty>
      <key>titlePage</key>
      <value>Producto final: descripción y material</value>
    </odeNavStructureProperty>
    <odeNavStructureProperty>
      <key>titleNode</key>
      <value>Producto final: descripción y material</value>
    </odeNavStructureProperty>
  </odeNavStructureProperties>
  <odePagStructures>
    <odePagStructure>
      <odePageId>page-1776612740113-wrve62d05</odePageId>
      <odeBlockId>block-1776612748736-k3y7d3epz</odeBlockId>
      <blockName>Información general</blockName>
      <iconName></iconName>
      <odePagStructureOrder>0</odePagStructureOrder>
      <odePagStructureProperties>
        <odePagStructureProperty>
          <key>visibility</key>
          <value>true</value>
        </odePagStructureProperty>
        <odePagStructureProperty>
          <key>teacherOnly</key>
          <value>false</value>
        </odePagStructureProperty>
        <odePagStructureProperty>
          <key>allowToggle</key>
          <value>true</value>
        </odePagStructureProperty>
        <odePagStructureProperty>
          <key>minimized</key>
          <value>false</value>
        </odePagStructureProperty>
        <odePagStructureProperty>
          <key>cssClass</key>
          <value></value>
        </odePagStructureProperty>
      </odePagStructureProperties>
      <odeComponents>
        <odeComponent>
          <odePageId>page-1776612740113-wrve62d05</odePageId>
          <odeBlockId>block-1776612748736-k3y7d3epz</odeBlockId>
          <odeIdeviceId>idevice-1776612748735-t4kv7i06n</odeIdeviceId>
          <odeIdeviceTypeName>text</odeIdeviceTypeName>
          <htmlView><![CDATA[<div class="exe-text-template">
    <figure class="exe-figure position-center" style="width: 200px;"><img src="https://upload.wikimedia.org/wikipedia/commons/1/18/Powtoon.jpg" title="Aplicación para el producto final" width="200" height="200" alt="Aplicación Powtoon" />
<figcaption class="figcaption"><span class="author">Wikimedia</span>. <a href="https://upload.wikimedia.org/wikipedia/commons/1/18/Powtoon.jpg" class="title" target="_blank" rel="noopener"><em>Powtoon</em></a> <span class="license"><span class="sep">(</span><a href="http://creativecommons.org/publicdomain/zero/1.0/deed.en" class="license" target="_blank" rel="noopener">CC0</a><span class="sep">)</span></span></figcaption>
</figure>
<p><strong>¿Cómo va a ser el producto final?</strong></p>
<p>El producto final consistirá en la creación de un vídeo mediante Powtoon, en el que el alumnado explorará la cultura y la historia de distintos países angloparlantes, estableciendo comparaciones con su propio contexto cultural.</p>
<p>Para su elaboración, se organizarán grupos cooperativos de cuatro alumnos, configurados de forma heterogénea para favorecer la inclusión, la colaboración y el aprendizaje entre iguales.</p>
</div>]]></htmlView>
          <jsonProperties><![CDATA[{"ideviceId":"idevice-1776612748735-t4kv7i06n","textInfoDurationInput":"","textInfoDurationTextInput":"Duración","textInfoParticipantsInput":"","textInfoParticipantsTextInput":"Agrupamiento","textTextarea":"<figure class=\"exe-figure position-center\" style=\"width: 200px;\"><img src=\"https://upload.wikimedia.org/wikipedia/commons/1/18/Powtoon.jpg\" title=\"Aplicación para el producto final\" width=\"200\" height=\"200\" alt=\"Aplicación Powtoon\" />\n<figcaption class=\"figcaption\"><span class=\"author\">Wikimedia</span>. <a href=\"https://upload.wikimedia.org/wikipedia/commons/1/18/Powtoon.jpg\" class=\"title\" target=\"_blank\" rel=\"noopener\"><em>Powtoon</em></a> <span class=\"license\"><span class=\"sep\">(</span><a href=\"http://creativecommons.org/publicdomain/zero/1.0/deed.en\" class=\"license\" target=\"_blank\" rel=\"noopener\">CC0</a><span class=\"sep\">)</span></span></figcaption>\n</figure>\n<p><strong>¿Cómo va a ser el producto final?</strong></p>\n<p>El producto final consistirá en la creación de un vídeo mediante Powtoon, en el que el alumnado explorará la cultura y la historia de distintos países angloparlantes, estableciendo comparaciones con su propio contexto cultural.</p>\n<p>Para su elaboración, se organizarán grupos cooperativos de cuatro alumnos, configurados de forma heterogénea para favorecer la inclusión, la colaboración y el aprendizaje entre iguales.</p>","textFeedbackInput":"Mostrar retroalimentación","textFeedbackTextarea":""}]]></jsonProperties>
          <odeComponentsOrder>0</odeComponentsOrder>
          <odeComponentsProperties>
          </odeComponentsProperties>
        </odeComponent>
        <odeComponent>
          <odePageId>page-1776612740113-wrve62d05</odePageId>
          <odeBlockId>block-1776612748736-k3y7d3epz</odeBlockId>
          <odeIdeviceId>idevice-1776615750202-z80r4nhhw</odeIdeviceId>
          <odeIdeviceTypeName>udl-content</odeIdeviceTypeName>
          <htmlView><![CDATA[<div class="exe-udlContent exe-udlContent-expression"><section class="exe-udlContent-block"><div class="exe-udlContent-content"><div class="exe-udlContent-content-main"><p><strong>¿No sabes de qué hablar?</strong></p>
<p>Puedes ver estos vídeos para inspirarte y hacer el proyecto. Además, siempre les puedes poner subtítulos si lo necesitas.&nbsp;</p>
<figure class="exe-figure exe-media position-center license-CC0" style="width: 300px;" id="fig_ov730xds5"><iframe width="300" height="150" src="https://www.youtube.com/embed/eJC75rducTo" allowfullscreen="allowfullscreen" data-mce-fragment="1"></iframe>
<figcaption class="figcaption"><a href="https://www.youtube.com/watch?v=eJC75rducTo" target="_blank" class="author" rel="noopener">Fun Facts by Polo</a>. <a href="https://www.youtube.com/watch?v=eJC75rducTo" target="_blank" class="title" rel="noopener"><em>Around the world: amazing traditions and cultures</em></a> <span class="license"><span class="sep">(</span><a href="http://creativecommons.org/publicdomain/zero/1.0/deed.en" rel="license nofollow noopener" target="_blank" title="Creative Commons (CC0)">CC0</a><span class="sep">)</span></span></figcaption>
</figure></div></div></section><section class="exe-udlContent-block"><div class="exe-udlContent-content"><div class="exe-udlContent-content-main"><p><strong>¿Powtoon te parece una herramienta muy complicada?</strong></p>
<p>Aquí tienes un tutorial para ayudarte con la tarea. Recuerda que puedes usar otras aplicaciones si quieres, pero siempre puedes intentar practicar con apps nuevas.</p>
<figure class="exe-figure exe-media position-center license-CC0" style="width: 560px;" id="fig_jgs678pbu"><iframe width="560" height="314" src="https://www.youtube.com/embed/ggR1n7YKoRo" allowfullscreen="allowfullscreen" data-mce-fragment="1"></iframe>
<figcaption class="figcaption"><span class="author">The Social Guide</span>. <a href="https://www.youtube.com/watch?v=ggR1n7YKoRo" target="_blank" class="title" rel="noopener"><em> Powtoon Tutorial For Beginners | How to Make Videos on Powtoon | Better than Doodly?</em></a> <span class="license"><span class="sep">(</span><a href="http://creativecommons.org/publicdomain/zero/1.0/deed.en" rel="license nofollow noopener" target="_blank" title="Creative Commons (CC0)">CC0</a><span class="sep">)</span></span></figcaption>
</figure></div></div></section></div>]]></htmlView>
          <jsonProperties></jsonProperties>
          <odeComponentsOrder>1</odeComponentsOrder>
          <odeComponentsProperties>
          </odeComponentsProperties>
        </odeComponent>
      </odeComponents>
    </odePagStructure>
    <odePagStructure>
      <odePageId>page-1776612740113-wrve62d05</odePageId>
      <odeBlockId>block-1776613111833-cwasoow0m</odeBlockId>
      <blockName>Normas básicas de seguridad digital</blockName>
      <iconName></iconName>
      <odePagStructureOrder>1</odePagStructureOrder>
      <odePagStructureProperties>
        <odePagStructureProperty>
          <key>visibility</key>
          <value>true</value>
        </odePagStructureProperty>
        <odePagStructureProperty>
          <key>teacherOnly</key>
          <value>false</value>
        </odePagStructureProperty>
        <odePagStructureProperty>
          <key>allowToggle</key>
          <value>true</value>
        </odePagStructureProperty>
        <odePagStructureProperty>
          <key>minimized</key>
          <value>false</value>
        </odePagStructureProperty>
        <odePagStructureProperty>
          <key>cssClass</key>
          <value></value>
        </odePagStructureProperty>
      </odePagStructureProperties>
      <odeComponents>
        <odeComponent>
          <odePageId>page-1776612740113-wrve62d05</odePageId>
          <odeBlockId>block-1776613111833-cwasoow0m</odeBlockId>
          <odeIdeviceId>idevice-1776613111831-17n5aw2g2</odeIdeviceId>
          <odeIdeviceTypeName>image-gallery</odeIdeviceTypeName>
          <htmlView><![CDATA[<!-- Idevice Example template start -->
<div class="exe-image-gallery-template">
  <!-- Idevice content start -->
  
            <div class="imageGallery-IDevice">
                <div class="imageGallery-body"><div id="imageContainer_0" class="imageContainer"> <a idevice-id="idevice-1776613111831-17n5aw2g2" title="" href="asset://d6d1c8f9-ab9c-6bbf-f4b5-784888bacba7.jpg" class="imageLink">  <div class="imageElement">   <img src="asset://d6d1c8f9-ab9c-6bbf-f4b5-784888bacba7.jpg" height="128" width="128" title="" alt="" titlelink="" author="" authorlink="" license="" licenselink=""/>  </div> </a></div>
                </div>
            </div>
  <!-- Idevice content end -->
</div>
<!-- Idevice Example template end -->]]></htmlView>
          <jsonProperties><![CDATA[{"ideviceId":"idevice-1776613111831-17n5aw2g2","img_0":{"img":"asset://d6d1c8f9-ab9c-6bbf-f4b5-784888bacba7.jpg","thumbnail":"asset://d6d1c8f9-ab9c-6bbf-f4b5-784888bacba7.jpg","title":"","linktitle":"","author":"","linkauthor":"","license":""}}]]></jsonProperties>
          <odeComponentsOrder>0</odeComponentsOrder>
          <odeComponentsProperties>
          </odeComponentsProperties>
        </odeComponent>
      </odeComponents>
    </odePagStructure>
    <odePagStructure>
      <odePageId>page-1776612740113-wrve62d05</odePageId>
      <odeBlockId>block-1776612951323-17z5k18pk</odeBlockId>
      <blockName>Tutoriales y apps para crear el vídeo</blockName>
      <iconName></iconName>
      <odePagStructureOrder>2</odePagStructureOrder>
      <odePagStructureProperties>
        <odePagStructureProperty>
          <key>visibility</key>
          <value>true</value>
        </odePagStructureProperty>
        <odePagStructureProperty>
          <key>teacherOnly</key>
          <value>false</value>
        </odePagStructureProperty>
        <odePagStructureProperty>
          <key>allowToggle</key>
          <value>true</value>
        </odePagStructureProperty>
        <odePagStructureProperty>
          <key>minimized</key>
          <value>false</value>
        </odePagStructureProperty>
        <odePagStructureProperty>
          <key>cssClass</key>
          <value></value>
        </odePagStructureProperty>
      </odePagStructureProperties>
      <odeComponents>
        <odeComponent>
          <odePageId>page-1776612740113-wrve62d05</odePageId>
          <odeBlockId>block-1776612951323-17z5k18pk</odeBlockId>
          <odeIdeviceId>idevice-1776612951320-akld57157</odeIdeviceId>
          <odeIdeviceTypeName>external-website</odeIdeviceTypeName>
          <htmlView><![CDATA[      <div id="iframeWebsiteIdevice">       <iframe src="https://padlet.com/paulacm15031996/actividad-5-1-z6dxuo9x22bsy6g3" size="4" width="600" height="800" style="width:100%;">      </iframe>      <div class="iframe-error-message" style="display:none;">No se puede mostrar un iframe en HTTP en una web HTTPS.</div>       </div>      ]]></htmlView>
          <jsonProperties></jsonProperties>
          <odeComponentsOrder>0</odeComponentsOrder>
          <odeComponentsProperties>
          </odeComponentsProperties>
        </odeComponent>
      </odeComponents>
    </odePagStructure>
    <odePagStructure>
      <odePageId>page-1776612740113-wrve62d05</odePageId>
      <odeBlockId>block-1776613009481-5vh3wupgf</odeBlockId>
      <blockName>Symbaloo: herramientas útiles</blockName>
      <iconName></iconName>
      <odePagStructureOrder>3</odePagStructureOrder>
      <odePagStructureProperties>
        <odePagStructureProperty>
          <key>visibility</key>
          <value>true</value>
        </odePagStructureProperty>
        <odePagStructureProperty>
          <key>teacherOnly</key>
          <value>false</value>
        </odePagStructureProperty>
        <odePagStructureProperty>
          <key>allowToggle</key>
          <value>true</value>
        </odePagStructureProperty>
        <odePagStructureProperty>
          <key>minimized</key>
          <value>false</value>
        </odePagStructureProperty>
        <odePagStructureProperty>
          <key>cssClass</key>
          <value></value>
        </odePagStructureProperty>
      </odePagStructureProperties>
      <odeComponents>
        <odeComponent>
          <odePageId>page-1776612740113-wrve62d05</odePageId>
          <odeBlockId>block-1776613009481-5vh3wupgf</odeBlockId>
          <odeIdeviceId>idevice-1776613009480-mnijh9hr4</odeIdeviceId>
          <odeIdeviceTypeName>external-website</odeIdeviceTypeName>
          <htmlView><![CDATA[      <div id="iframeWebsiteIdevice">       <iframe src="https://www.symbaloo.com/shared/AAAABoJp_e0AA42ADtGx3w==" size="1" width="600" height="200" style="width:100%;">      </iframe>      <div class="iframe-error-message" style="display:none;">No se puede mostrar un iframe en HTTP en una web HTTPS.</div>       </div>      ]]></htmlView>
          <jsonProperties></jsonProperties>
          <odeComponentsOrder>0</odeComponentsOrder>
          <odeComponentsProperties>
          </odeComponentsProperties>
        </odeComponent>
      </odeComponents>
    </odePagStructure>
    <odePagStructure>
      <odePageId>page-1776612740113-wrve62d05</odePageId>
      <odeBlockId>block-1776613373833-093zeurw6</odeBlockId>
      <blockName>Checklist de coevaluación</blockName>
      <iconName></iconName>
      <odePagStructureOrder>4</odePagStructureOrder>
      <odePagStructureProperties>
        <odePagStructureProperty>
          <key>visibility</key>
          <value>true</value>
        </odePagStructureProperty>
        <odePagStructureProperty>
          <key>teacherOnly</key>
          <value>false</value>
        </odePagStructureProperty>
        <odePagStructureProperty>
          <key>allowToggle</key>
          <value>true</value>
        </odePagStructureProperty>
        <odePagStructureProperty>
          <key>minimized</key>
          <value>false</value>
        </odePagStructureProperty>
        <odePagStructureProperty>
          <key>cssClass</key>
          <value></value>
        </odePagStructureProperty>
      </odePagStructureProperties>
      <odeComponents>
        <odeComponent>
          <odePageId>page-1776612740113-wrve62d05</odePageId>
          <odeBlockId>block-1776613373833-093zeurw6</odeBlockId>
          <odeIdeviceId>idevice-1776613373830-gy91yhy3r</odeIdeviceId>
          <odeIdeviceTypeName>checklist</odeIdeviceTypeName>
          <htmlView><![CDATA[<div class="listacotejo-IDevice"><div class="listacotejo-instructions CTJ-instructions"><p>Completa la lista de cotejo marcando las casillas al realizar las actividades correspondientes.</p></div><div class="listacotejo-DataGame js-hidden">%E9%B0%E6%EB%E2%F7%D5%F3%FF%F7%B0%A8%B0%D1%FD%E6%F7%F8%FD%B0%BE%B0%FB%F6%B0%A8%B0%FB%F6%F7%E4%FB%F1%F7%BF%A3%A5%A5%A4%A4%A3%A1%A1%A5%A1%AA%A1%A2%BF%F5%EB%AB%A3%EB%FA%EB%A1%E0%B0%BE%B0%E6%FB%E6%FE%F7%B0%A8%B0%D1%FA%F7%F1%F9%FE%FB%E1%E6%B2%F6%F7%B2%F1%FD%F7%E4%F3%FE%E7%F3%F1%FBa%FC%B0%BE%B0%E1%E7%F0%E6%FB%E6%FE%F7%B0%A8%B0%B0%BE%B0%FE%F7%E4%F7%FE%E1%B0%A8%C9%E9%B0%E6%EB%E2%F7%B0%A8%B0%A2%B0%BE%B0%FC%FB%E4%F7%FE%B0%A8%B0%A2%B0%BE%B0%FB%E6%F7%FF%B0%A8%B0%D7%FE%B2%E6%E0%F3%F0%F3%F8%FD%B2%E6%FB%F7%FC%F7%B2%E6%FD%F6%FD%E1%B2%FE%FD%E1%B2%E2%E7%FC%E6%FD%E1%B2%F6%F7%B2%FE%F3%E1%B2%FB%FC%E1%E6%E0%E7%F1%F1%FB%FD%FC%F7%E1%BC%B0%BE%B0%E2%FD%FB%FC%E6%E1%B0%A8%B0%A3%B0%EF%BE%E9%B0%E6%EB%E2%F7%B0%A8%B0%A2%B0%BE%B0%FC%FB%E4%F7%FE%B0%A8%B0%A2%B0%BE%B0%FB%E6%F7%FF%B0%A8%B0%AE%E1%E2%F3%FC%B2%E1%E6%EB%FE%F7%AF%CE%B0%F0%F3%F1%F9%F5%E0%FD%E7%FC%F6%BF%F1%FD%FE%FD%E0%A8%B2%E0%F5%F0%BA%A0%A7%A7%BE%B2%A0%A7%A7%BE%B2%A0%A7%A7%BB%A9%CE%B0%AC%C1%F7%B2%FB%FC%F1%FE%E7%EB%F7%FC%B2%FE%FD%E1%B2%F6%F7%E6%F3%FE%FE%F7%E1%B2%FB%FF%E2%FD%E0%E6%F3%FC%E6%F7%E1%BC%AE%BD%E1%E2%F3%FC%AC%B0%BE%B0%E2%FD%FB%FC%E6%E1%B0%A8%B0%A3%B0%EF%BE%E9%B0%E6%EB%E2%F7%B0%A8%B0%A2%B0%BE%B0%FC%FB%E4%F7%FE%B0%A8%B0%A2%B0%BE%B0%FB%E6%F7%FF%B0%A8%B0%DE%F3%E1%B2%FB%F6%F7%F3%E1%B2%F7%E1%E6s%FC%B2%FD%E0%F6%F7%FC%F3%F6%F3%E1%B2%EB%B2%E1%F7%B2%F7%FC%E6%FB%F7%FC%F6%F7%FC%B2%F0%FB%F7%FC%BC%B0%BE%B0%E2%FD%FB%FC%E6%E1%B0%A8%B0%A3%B0%EF%BE%E9%B0%E6%EB%E2%F7%B0%A8%B0%A2%B0%BE%B0%FC%FB%E4%F7%FE%B0%A8%B0%A2%B0%BE%B0%FB%E6%F7%FF%B0%A8%B0%AE%E1%E2%F3%FC%B2%E1%E6%EB%FE%F7%AF%CE%B0%F0%F3%F1%F9%F5%E0%FD%E7%FC%F6%BF%F1%FD%FE%FD%E0%A8%B2%E0%F5%F0%BA%A0%A7%A7%BE%B2%A0%A7%A7%BE%B2%A0%A7%A7%BB%A9%CE%B0%AC%DE%FD%E1%B2%E1%E7%F0%E6%7F%E6%E7%FE%FD%E1%B2%E1%FD%FC%B2%F1%FE%F3%E0%FD%E1%B2%EB%B2%E1%F7%B2%F7%FC%E6%FB%F7%FC%F6%F7%E1%BC%AE%BD%E1%E2%F3%FC%AC%B0%BE%B0%E2%FD%FB%FC%E6%E1%B0%A8%B0%A3%B0%EF%BE%E9%B0%E6%EB%E2%F7%B0%A8%B0%A2%B0%BE%B0%FC%FB%E4%F7%FE%B0%A8%B0%A2%B0%BE%B0%FB%E6%F7%FF%B0%A8%B0%C7%E1%F3%FC%B2%FB%FC%F5%FE%7B%E1%B2%F6%E7%E0%F3%FC%E6%F7%B2%E6%FD%F6%FD%B2%F7%FE%B2%E4%7F%F6%F7%FD%BC%B0%BE%B0%E2%FD%FB%FC%E6%E1%B0%A8%B0%A3%B0%EF%BE%E9%B0%E6%EB%E2%F7%B0%A8%B0%A2%B0%BE%B0%FC%FB%E4%F7%FE%B0%A8%B0%A2%B0%BE%B0%FB%E6%F7%FF%B0%A8%B0%AE%E1%E2%F3%FC%B2%E1%E6%EB%FE%F7%AF%CE%B0%F0%F3%F1%F9%F5%E0%FD%E7%FC%F6%BF%F1%FD%FE%FD%E0%A8%B2%E0%F5%F0%BA%A0%A7%A7%BE%B2%A0%A7%A7%BE%B2%A0%A7%A7%BB%A9%CE%B0%AC%D7%FE%B2%E4%FD%F1%F3%F0%E7%FE%F3%E0%FB%FD%B2%F7%E1%B2%F3%F6%F7%F1%E7%F3%F6%FD%B2%F3%FE%B2%E6%F7%FF%F3%BC%AE%BD%E1%E2%F3%FC%AC%B0%BE%B0%E2%FD%FB%FC%E6%E1%B0%A8%B0%A3%B0%EF%BE%E9%B0%E6%EB%E2%F7%B0%A8%B0%A2%B0%BE%B0%FC%FB%E4%F7%FE%B0%A8%B0%A2%B0%BE%B0%FB%E6%F7%FF%B0%A8%B0%DE%F3%B2%E2%E0%FD%FC%E7%FC%F1%FB%F3%F1%FBa%FC%B2%F7%E1%B2%F1%FE%F3%E0%F3%B2%EB%B2%F1%FD%FF%E2%E0%F7%FC%E1%FB%F0%FE%F7%BC%B0%BE%B0%E2%FD%FB%FC%E6%E1%B0%A8%B0%A3%B0%EF%BE%E9%B0%E6%EB%E2%F7%B0%A8%B0%A2%B0%BE%B0%FC%FB%E4%F7%FE%B0%A8%B0%A2%B0%BE%B0%FB%E6%F7%FF%B0%A8%B0%C6%FD%F6%FD%E1%B2%FE%FD%E1%B2%FF%FB%F7%FF%F0%E0%FD%E1%B2%F3%E2%F3%E0%F7%F1%F7%FC%B2%EB%B2%FA%F3%F0%FE%F3%FC%BC%B0%BE%B0%E2%FD%FB%FC%E6%E1%B0%A8%B0%A3%B0%EF%BE%E9%B0%E6%EB%E2%F7%B0%A8%B0%A2%B0%BE%B0%FC%FB%E4%F7%FE%B0%A8%B0%A2%B0%BE%B0%FB%E6%F7%FF%B0%A8%B0%AE%E1%E2%F3%FC%B2%E1%E6%EB%FE%F7%AF%CE%B0%F0%F3%F1%F9%F5%E0%FD%E7%FC%F6%BF%F1%FD%FE%FD%E0%A8%B2%E0%F5%F0%BA%A0%A1%AA%BE%B2%A0%A1%AA%BE%B2%A0%A1%AA%BB%A9%CE%B0%AC%D7%FE%B2%E6%FB%F7%FF%E2%FD%B2%F6%F7%B2%E2%F3%E0%E6%FB%F1%FB%E2%F3%F1%FBa%FC%B2%F7%E1%E6s%B2%F0%FB%F7%FC%B2%E0%F7%E2%F3%E0%E6%FB%F6%FD%BC%AE%BD%E1%E2%F3%FC%AC%B0%BE%B0%E2%FD%FB%FC%E6%E1%B0%A8%B0%A3%B0%EF%BE%E9%B0%E6%EB%E2%F7%B0%A8%B0%A2%B0%BE%B0%FC%FB%E4%F7%FE%B0%A8%B0%A2%B0%BE%B0%FB%E6%F7%FF%B0%A8%B0%C1%F7%B2%FC%FD%E6%F3%B2%E2%E0%F7%E2%F3%E0%F3%F1%FBa%FC%B2%EB%B2%E6%E0%F3%F0%F3%F8%FD%B2%F7%FC%B2%F7%E3%E7%FB%E2%FD%BC%B0%BE%B0%E2%FD%FB%FC%E6%E1%B0%A8%B0%A3%B0%EF%BE%E9%B0%E6%EB%E2%F7%B0%A8%B0%A2%B0%BE%B0%FC%FB%E4%F7%FE%B0%A8%B0%A2%B0%BE%B0%FB%E6%F7%FF%B0%A8%B0%D7%FE%B2%E4%7F%F6%F7%FD%B2%F7%E1%E6s%B2%F0%FB%F7%FC%B2%F7%F6%FB%E6%F3%F6%FD%BC%B0%BE%B0%E2%FD%FB%FC%E6%E1%B0%A8%B0%A3%B0%EF%BE%E9%B0%E6%EB%E2%F7%B0%A8%B0%A2%B0%BE%B0%FC%FB%E4%F7%FE%B0%A8%B0%A2%B0%BE%B0%FB%E6%F7%FF%B0%A8%B0%AE%E1%E2%F3%FC%B2%E1%E6%EB%FE%F7%AF%CE%B0%F0%F3%F1%F9%F5%E0%FD%E7%FC%F6%BF%F1%FD%FE%FD%E0%A8%B2%E0%F5%F0%BA%A0%A7%A7%BE%B2%A0%A7%A7%BE%B2%A0%A7%A7%BB%A9%CE%B0%AC%C1%F7%B2%F7%E1%F1%E7%F1%FA%F3%B2%EB%B2%E1%F7%B2%E4%F7%B2%F1%FD%E0%E0%F7%F1%E6%F3%FF%F7%FC%E6%F7%BC%AE%BD%E1%E2%F3%FC%AC%B0%BE%B0%E2%FD%FB%FC%E6%E1%B0%A8%B0%A3%B0%EF%BE%E9%B0%E6%EB%E2%F7%B0%A8%B0%A2%B0%BE%B0%FC%FB%E4%F7%FE%B0%A8%B0%A2%B0%BE%B0%FB%E6%F7%FF%B0%A8%B0%D7%FE%B2%E4%7F%F6%F7%FD%B2%E6%FB%F7%FC%F7%B2%E7%FC%F3%B2%F6%E7%E0%F3%F1%FBa%FC%B2%F3%F6%F7%F1%E7%F3%F6%F3%BC%B0%BE%B0%E2%FD%FB%FC%E6%E1%B0%A8%B0%A3%B0%EF%BE%E9%B0%E6%EB%E2%F7%B0%A8%B0%A3%B0%BE%B0%FC%FB%E4%F7%FE%B0%A8%B0%A2%B0%BE%B0%FB%E6%F7%FF%B0%A8%B0%D3%FE%F5%FD%B2%E3%E7%F7%B2%E2%E7%F7%F6%F7%FC%B2%FF%F7%F8%FD%E0%F3%E0%A8%B0%BE%B0%E2%FD%FB%FC%E6%E1%B0%A8%B0%A3%B0%EF%BE%E9%B0%E6%EB%E2%F7%B0%A8%B0%A3%B0%BE%B0%FC%FB%E4%F7%FE%B0%A8%B0%A2%B0%BE%B0%FB%E6%F7%FF%B0%A8%B0%DE%FD%B2%E3%E7%F7%B2%FFs%E1%B2%FF%F7%B2%FA%F3%B2%F5%E7%E1%E6%F3%F6%FD%B2%FA%F3%B2%E1%FB%F6%FD%A8%B0%BE%B0%E2%FD%FB%FC%E6%E1%B0%A8%B0%A3%B0%EF%CF%BE%B0%FA%F3%E1%DE%FD%F5%FD%B0%A8%F4%F3%FE%E1%F7%BE%B0%E7%E0%FE%DE%FD%F5%FD%B0%A8%B0%B0%BE%B0%FA%F3%E1%D1%FD%FF%FF%E7%FC%FB%E6%EB%B0%A8%F4%F3%FE%E1%F7%BE%B0%E7%E0%FE%D1%FD%FF%FF%E7%FC%FB%E6%EB%B0%A8%B0%B0%BE%B0%FA%F3%E1%D6%F7%F1%FD%E0%F3%E6%FB%E4%F7%B0%A8%F4%F3%FE%E1%F7%BE%B0%E7%E0%FE%D6%F7%F1%FD%E0%F3%E6%FB%E4%F7%B0%A8%B0%B0%BE%B0%E1%F3%E4%F7%D6%F3%E6%F3%B0%A8%E6%E0%E7%F7%BE%B0%E7%E1%F7%E0%D6%F3%E6%F3%B0%A8%E6%E0%E7%F7%BE%B0%F4%FD%FD%E6%F7%E0%B0%A8%B0%D7%E1%E6%F3%B2%AE%F3%B2%FA%E0%F7%F4%AF%FA%E6%E6%E2%E1%A8%BD%BD%F7%E1%BC%E5%FB%F9%FB%E2%F7%F6%FB%F3%BC%FD%E0%F5%BD%E5%FB%F9%FB%BD%DE%FB%E1%E6%F3%CD%F6%F7%CD%F1%FD%FF%E2%E0%FD%F0%F3%F1%FB%B7%D1%A1%B7%D0%A1%FC%AC%FE%FB%E1%E6%F3%B2%F6%F7%B2%F1%FD%E6%F7%F8%FD%AE%BD%F3%AC%B2%E1%F7%B2%F7%FC%F1%E7%F7%FC%E6%E0%F3%B2%F0%F3%F8%FD%B2%E7%FC%F3%B2%FE%FB%F1%F7%FC%F1%FB%F3%AE%BD%F0%E0%AC%AE%F3%B2%FA%E0%F7%F4%AF%FA%E6%E6%E2%A8%BD%BD%F1%E0%F7%F3%E6%FB%E4%F7%F1%FD%FF%FF%FD%FC%E1%BC%FD%E0%F5%BD%FE%FB%F1%F7%FC%E1%F7%E1%BD%F0%EB%BF%E1%F3%BD%A6%BC%A2%AC%D1%E0%F7%F3%E6%FB%E4%F7%B2%D1%FD%FF%FF%FD%FC%E1%B2%C0%F7%F1%FD%FC%FD%F1%FB%FF%FB%F7%FC%E6%FD%BF%D1%FD%FF%E2%F3%E0%E6%FB%E0%B2%FB%F5%E7%F3%FE%B2%A6%BC%A2%B2%DB%FC%E6%F7%E0%FC%F3%E6%FB%FD%FC%F3%FE%B2%DE%FB%F1%F7%FC%E1%F7%AE%BD%F3%AC%B0%BE%B0%E7%E1%F7%C1%F1%FD%E0%F7%B0%A8%E6%E0%E7%F7%BE%B0%FF%E1%F5%E1%B0%A8%E9%B0%FF%E1%F5%D1%FD%FF%E2%FE%FB%E6%B0%A8%B0%D1%FD%FF%E2%FE%F7%E6%F3%F6%F3%E1%B0%BE%B0%FF%E1%F5%D6%FD%FC%F7%B0%A8%B0%DA%F7%F1%FA%FD%B0%BE%B0%FF%E1%F5%DB%FC%C2%E0%FD%F5%E0%F7%E1%E1%B0%A8%B0%D7%FC%B2%E2%E0%FD%F1%F7%E1%FD%B0%BE%B0%FF%E1%F5%C7%FC%E0%F7%F3%FE%FB%E8%F7%F6%B0%A8%B0%C1%FB%FC%B2%F1%FD%FF%E2%FE%F7%E6%F3%E0%B0%BE%B0%FF%E1%F5%E6%F3%E1%F9%DC%E7%FF%F0%F7%E0%B0%A8%B0%DCh%FF%F7%E0%FD%B2%F6%F7%B2%E6%F3%E0%F7%F3%E1%B0%BE%B0%FF%E1%F5%DC%F3%FF%F7%B0%A8%B0%DC%FD%FF%F0%E0%F7%B0%BE%B0%FF%E1%F5%D6%F3%E6%F7%B0%A8%B0%D4%F7%F1%FA%F3%B0%BE%B0%FF%E1%F5%C1%F3%E4%F7%B0%A8%B0%D6%F7%E1%F1%F3%E0%F5%F3%E0%B0%BE%B0%FF%E1%F5%DE%FB%E1%E6%B0%A8%B0%FE%FB%E1%E6%F3%CD%F6%F7%CD%F1%FD%E6%F7%F8%FD%B0%BE%B0%FF%E1%F5%C1%F1%FD%E0%F7%B0%A8%B0%C2%E7%FC%E6%E7%F3%F1%FBa%FC%B0%BE%B0%FF%E1%F5%C5%F7%FB%F5%FA%E6%B0%A8%B0%C2%F7%E1%FD%B0%BE%B0%FF%E1%F5%C2%FD%FB%FC%E6%E1%B0%A8%B0%E2%E7%FC%E6%FD%E1%B0%BE%B0%FF%E1%F5%C2%FD%FB%FC%E6%B0%A8%B0%E2%E7%FC%E6%FD%B0%BE%B0%FF%E1%F5%C0%F7%F0%FD%FD%E6%B0%A8%B0%C0%F7%FB%FC%FB%F1%FB%F3%E0%B0%BE%B0%FF%E1%F5%D6%F7%FE%F7%E6%F7%B0%A8%B0-%C1%F7%F5%E7%E0%FD%B2%E3%E7%F7%B2%F6%F7%E1%F7%F3%B2%F0%FD%E0%E0%F3%E0%B2%E6%FD%F6%FD%E1%B2%FE%FD%E1%B2%F1%F3%FF%E2%FD%E1%B2%F6%F7%FE%B2%F4%FD%E0%FF%E7%FE%F3%E0%FB%FD%AD%B0%EF%EF</div><div class="listacotejo-bns js-hidden">Navegador incompatible</div><div class="listacotejo-extra-content"><p>¡Gracias por tu colaboración y sinceridad!</p></div></div>]]></htmlView>
          <jsonProperties></jsonProperties>
          <odeComponentsOrder>0</odeComponentsOrder>
          <odeComponentsProperties>
          </odeComponentsProperties>
        </odeComponent>
      </odeComponents>
    </odePagStructure>
    <odePagStructure>
      <odePageId>page-1776612740113-wrve62d05</odePageId>
      <odeBlockId>block-1776613233706-411jloe48</odeBlockId>
      <blockName>Línea temporal de nuestro trabajo</blockName>
      <iconName></iconName>
      <odePagStructureOrder>5</odePagStructureOrder>
      <odePagStructureProperties>
        <odePagStructureProperty>
          <key>visibility</key>
          <value>true</value>
        </odePagStructureProperty>
        <odePagStructureProperty>
          <key>teacherOnly</key>
          <value>false</value>
        </odePagStructureProperty>
        <odePagStructureProperty>
          <key>allowToggle</key>
          <value>true</value>
        </odePagStructureProperty>
        <odePagStructureProperty>
          <key>minimized</key>
          <value>false</value>
        </odePagStructureProperty>
        <odePagStructureProperty>
          <key>cssClass</key>
          <value></value>
        </odePagStructureProperty>
      </odePagStructureProperties>
      <odeComponents>
        <odeComponent>
          <odePageId>page-1776612740113-wrve62d05</odePageId>
          <odeBlockId>block-1776613233706-411jloe48</odeBlockId>
          <odeIdeviceId>idevice-1776613233703-lg9xvk6x3</odeIdeviceId>
          <odeIdeviceTypeName>external-website</odeIdeviceTypeName>
          <htmlView><![CDATA[      <div id="iframeWebsiteIdevice">       <iframe src="https://www.mindomo.com/mindmap/into-the-unknown-643d865070e14028adc8b20148a9b61b" size="3" width="600" height="500" style="width:100%;">      </iframe>      <div class="iframe-error-message" style="display:none;">No se puede mostrar un iframe en HTTP en una web HTTPS.</div>       </div>      ]]></htmlView>
          <jsonProperties></jsonProperties>
          <odeComponentsOrder>0</odeComponentsOrder>
          <odeComponentsProperties>
          </odeComponentsProperties>
        </odeComponent>
      </odeComponents>
    </odePagStructure>
    <odePagStructure>
      <odePageId>page-1776612740113-wrve62d05</odePageId>
      <odeBlockId>block-1776613962402-4kkssxz0z</odeBlockId>
      <blockName>Rúbrica</blockName>
      <iconName></iconName>
      <odePagStructureOrder>6</odePagStructureOrder>
      <odePagStructureProperties>
        <odePagStructureProperty>
          <key>visibility</key>
          <value>true</value>
        </odePagStructureProperty>
        <odePagStructureProperty>
          <key>teacherOnly</key>
          <value>false</value>
        </odePagStructureProperty>
        <odePagStructureProperty>
          <key>allowToggle</key>
          <value>true</value>
        </odePagStructureProperty>
        <odePagStructureProperty>
          <key>minimized</key>
          <value>false</value>
        </odePagStructureProperty>
        <odePagStructureProperty>
          <key>cssClass</key>
          <value></value>
        </odePagStructureProperty>
      </odePagStructureProperties>
      <odeComponents>
        <odeComponent>
          <odePageId>page-1776612740113-wrve62d05</odePageId>
          <odeBlockId>block-1776613962402-4kkssxz0z</odeBlockId>
          <odeIdeviceId>idevice-1776613962400-69ctsslzu</odeIdeviceId>
          <odeIdeviceTypeName>rubric</odeIdeviceTypeName>
          <htmlView><![CDATA[<div class="rubric-IDevice"><div class="exe-rubrics-instructions gameQP-instructions"><p>Con esta rúbrica, el profesor va a evaluar tu trabajo final. Estudia los apartados para saber qué se te pide en cada momento.</p></div><div class="rubric"><div class="exe-rubrics-DataGame js-hidden">%7B%22typeGame%22%3A%22Rubric%22%2C%22version%22%3A2%2C%22id%22%3A%22idevice-1776613962400-69ctsslzu%22%2C%22table%22%3A%7B%22title%22%3A%22R%FAbrica%20de%20ejemplo%20%284x4%29%22%2C%22categories%22%3A%5B%22Gram%E1tica%22%2C%22Vocabulario%22%2C%22Contenido%22%2C%22Originalidad%20y%20creatividad%22%2C%22Calidad%20del%20v%EDdeo%22%2C%22Dicci%F3n%22%2C%22Trabajo%20en%20equipo%22%2C%22Guion%2C%20plan%22%5D%2C%22scores%22%3A%5B%22Excelente%22%2C%22Notable%22%2C%22Suficiente%22%2C%22Insuficiente%22%5D%2C%22descriptions%22%3A%5B%5B%7B%22weight%22%3A%221.5%22%2C%22text%22%3A%22Uso%20casi%20perfecto%2C%20errores%20m%EDnimos%22%7D%2C%7B%22weight%22%3A%221%22%2C%22text%22%3A%22Poros%20errores%2C%20buena%20correcci%F3n.%22%7D%2C%7B%22weight%22%3A%220.5%22%2C%22text%22%3A%22Algunos%20errores%2C%20mensaje%20comprensible.%22%7D%2C%7B%22weight%22%3A%220%22%2C%22text%22%3A%22Errores%20frecuentes%2C%20dif%EDcil%20de%20comprender.%22%7D%5D%2C%5B%7B%22weight%22%3A%221.5%22%2C%22text%22%3A%22Vocabulario%20amplio%2C%20preciso%20y%20apropiado.%22%7D%2C%7B%22weight%22%3A%221%22%2C%22text%22%3A%22Variedad%20y%20precisi%F3n%20aceptables.%22%7D%2C%7B%22weight%22%3A%220.5%22%2C%22text%22%3A%22Vocabulario%20b%E1sico%20pero%20adecuado.%22%7D%2C%7B%22weight%22%3A%220%22%2C%22text%22%3A%22Vocabulario%20muy%20limitado%20o%20inadecuado.%22%7D%5D%2C%5B%7B%22weight%22%3A%222%22%2C%22text%22%3A%22Contenido%20completo%2C%20bien%20estructurado%20y%20profundo.%22%7D%2C%7B%22weight%22%3A%221.5%22%2C%22text%22%3A%22Contenido%20claro%2C%20relevante%20y%20organizado.%22%7D%2C%7B%22weight%22%3A%220.75%22%2C%22text%22%3A%22Ideas%20simples%20y%20claras%2C%20pero%20poco%20desarrolladas.%22%7D%2C%7B%22weight%22%3A%220%22%2C%22text%22%3A%22Ideas%20incompletas%2C%20incoherentes%20o%20irrelevantes.%22%7D%5D%2C%5B%7B%22weight%22%3A%221%22%2C%22text%22%3A%22Enfoque%20creativo%2C%20%FAnico%20y%20personal.%22%7D%2C%7B%22weight%22%3A%220.5%22%2C%22text%22%3A%22Algunas%20ideas%20originales.%22%7D%2C%7B%22weight%22%3A%220.25%22%2C%22text%22%3A%22Ideas%20b%E1sicas%2C%20con%20poca%20aportaci%F3n%20personal.%22%7D%2C%7B%22weight%22%3A%220%22%2C%22text%22%3A%22Sin%20creatividad%20o%20copia%20evidente.%22%7D%5D%2C%5B%7B%22weight%22%3A%221%22%2C%22text%22%3A%22Excelente%20calidad%20y%20cuidado%20t%E9cnico.%22%7D%2C%7B%22weight%22%3A%220.5%22%2C%22text%22%3A%22Buena%20calidad%2C%20fallos%20m%EDnimos.%22%7D%2C%7B%22weight%22%3A%220.25%22%2C%22text%22%3A%22Calidad%20aceptable%20con%20algunos%20fallos.%22%7D%2C%7B%22weight%22%3A%220.25%22%2C%22text%22%3A%22Sonido%20o%20imagen%20dificultan%20la%20comprensi%F3n.%22%7D%5D%2C%5B%7B%22weight%22%3A%222%22%2C%22text%22%3A%22Natural%2C%20fluido%20y%20con%20excelente%20entonaci%F3n.%22%7D%2C%7B%22weight%22%3A%221.5%22%2C%22text%22%3A%22Buena%20fluidez%20y%20pronunciaci%F3n%20clara.%22%7D%2C%7B%22weight%22%3A%220.75%22%2C%22text%22%3A%22Fluidez%20b%E1sica%2C%20pronunciaci%F3n%20correcta%20a%20veces.%22%7D%2C%7B%22weight%22%3A%220%22%2C%22text%22%3A%22Fluidez%20muy%20baja%2C%20dif%EDcil%20de%20entender.%22%7D%5D%2C%5B%7B%22weight%22%3A%220.5%22%2C%22text%22%3A%22Excelente%20coordinaci%F3n%20y%20participaci%F3n%20equilibrada.%22%7D%2C%7B%22weight%22%3A%220.3%22%2C%22text%22%3A%22Buena%20colaboraci%F3n%2C%20la%20mayor%EDa%20participa.%22%7D%2C%7B%22weight%22%3A%220.15%22%2C%22text%22%3A%22Participaci%F3n%20m%EDnima%20pero%20repartida.%22%7D%2C%7B%22weight%22%3A%220%22%2C%22text%22%3A%22Participaci%F3n%20desigual%2C%20sin%20colaboraci%F3n.%22%7D%5D%2C%5B%7B%22weight%22%3A%220.5%22%2C%22text%22%3A%22Planificaci%F3n%20detallada%20y%20guion%20coherente%20y%20s%F3lido.%22%7D%2C%7B%22weight%22%3A%220.3%22%2C%22text%22%3A%22Planificaci%F3n%20clara%2C%20estructura%20l%F3gica.%22%7D%2C%7B%22weight%22%3A%220.15%22%2C%22text%22%3A%22Planificaci%F3n%20b%E1sica%2C%20ideas%20poco%20conectadas.%22%7D%2C%7B%22weight%22%3A%220%22%2C%22text%22%3A%22Sin%20evidencia%20de%20planificaci%F3n.%22%7D%5D%5D%7D%2C%22title%22%3A%22R%FAbrica%20de%20ejemplo%20%284x4%29%22%2C%22categories%22%3A%5B%22Gram%E1tica%22%2C%22Vocabulario%22%2C%22Contenido%22%2C%22Originalidad%20y%20creatividad%22%2C%22Calidad%20del%20v%EDdeo%22%2C%22Dicci%F3n%22%2C%22Trabajo%20en%20equipo%22%2C%22Guion%2C%20plan%22%5D%2C%22scores%22%3A%5B%22Excelente%22%2C%22Notable%22%2C%22Suficiente%22%2C%22Insuficiente%22%5D%2C%22descriptions%22%3A%5B%5B%7B%22weight%22%3A%221.5%22%2C%22text%22%3A%22Uso%20casi%20perfecto%2C%20errores%20m%EDnimos%22%7D%2C%7B%22weight%22%3A%221%22%2C%22text%22%3A%22Poros%20errores%2C%20buena%20correcci%F3n.%22%7D%2C%7B%22weight%22%3A%220.5%22%2C%22text%22%3A%22Algunos%20errores%2C%20mensaje%20comprensible.%22%7D%2C%7B%22weight%22%3A%220%22%2C%22text%22%3A%22Errores%20frecuentes%2C%20dif%EDcil%20de%20comprender.%22%7D%5D%2C%5B%7B%22weight%22%3A%221.5%22%2C%22text%22%3A%22Vocabulario%20amplio%2C%20preciso%20y%20apropiado.%22%7D%2C%7B%22weight%22%3A%221%22%2C%22text%22%3A%22Variedad%20y%20precisi%F3n%20aceptables.%22%7D%2C%7B%22weight%22%3A%220.5%22%2C%22text%22%3A%22Vocabulario%20b%E1sico%20pero%20adecuado.%22%7D%2C%7B%22weight%22%3A%220%22%2C%22text%22%3A%22Vocabulario%20muy%20limitado%20o%20inadecuado.%22%7D%5D%2C%5B%7B%22weight%22%3A%222%22%2C%22text%22%3A%22Contenido%20completo%2C%20bien%20estructurado%20y%20profundo.%22%7D%2C%7B%22weight%22%3A%221.5%22%2C%22text%22%3A%22Contenido%20claro%2C%20relevante%20y%20organizado.%22%7D%2C%7B%22weight%22%3A%220.75%22%2C%22text%22%3A%22Ideas%20simples%20y%20claras%2C%20pero%20poco%20desarrolladas.%22%7D%2C%7B%22weight%22%3A%220%22%2C%22text%22%3A%22Ideas%20incompletas%2C%20incoherentes%20o%20irrelevantes.%22%7D%5D%2C%5B%7B%22weight%22%3A%221%22%2C%22text%22%3A%22Enfoque%20creativo%2C%20%FAnico%20y%20personal.%22%7D%2C%7B%22weight%22%3A%220.5%22%2C%22text%22%3A%22Algunas%20ideas%20originales.%22%7D%2C%7B%22weight%22%3A%220.25%22%2C%22text%22%3A%22Ideas%20b%E1sicas%2C%20con%20poca%20aportaci%F3n%20personal.%22%7D%2C%7B%22weight%22%3A%220%22%2C%22text%22%3A%22Sin%20creatividad%20o%20copia%20evidente.%22%7D%5D%2C%5B%7B%22weight%22%3A%221%22%2C%22text%22%3A%22Excelente%20calidad%20y%20cuidado%20t%E9cnico.%22%7D%2C%7B%22weight%22%3A%220.5%22%2C%22text%22%3A%22Buena%20calidad%2C%20fallos%20m%EDnimos.%22%7D%2C%7B%22weight%22%3A%220.25%22%2C%22text%22%3A%22Calidad%20aceptable%20con%20algunos%20fallos.%22%7D%2C%7B%22weight%22%3A%220.25%22%2C%22text%22%3A%22Sonido%20o%20imagen%20dificultan%20la%20comprensi%F3n.%22%7D%5D%2C%5B%7B%22weight%22%3A%222%22%2C%22text%22%3A%22Natural%2C%20fluido%20y%20con%20excelente%20entonaci%F3n.%22%7D%2C%7B%22weight%22%3A%221.5%22%2C%22text%22%3A%22Buena%20fluidez%20y%20pronunciaci%F3n%20clara.%22%7D%2C%7B%22weight%22%3A%220.75%22%2C%22text%22%3A%22Fluidez%20b%E1sica%2C%20pronunciaci%F3n%20correcta%20a%20veces.%22%7D%2C%7B%22weight%22%3A%220%22%2C%22text%22%3A%22Fluidez%20muy%20baja%2C%20dif%EDcil%20de%20entender.%22%7D%5D%2C%5B%7B%22weight%22%3A%220.5%22%2C%22text%22%3A%22Excelente%20coordinaci%F3n%20y%20participaci%F3n%20equilibrada.%22%7D%2C%7B%22weight%22%3A%220.3%22%2C%22text%22%3A%22Buena%20colaboraci%F3n%2C%20la%20mayor%EDa%20participa.%22%7D%2C%7B%22weight%22%3A%220.15%22%2C%22text%22%3A%22Participaci%F3n%20m%EDnima%20pero%20repartida.%22%7D%2C%7B%22weight%22%3A%220%22%2C%22text%22%3A%22Participaci%F3n%20desigual%2C%20sin%20colaboraci%F3n.%22%7D%5D%2C%5B%7B%22weight%22%3A%220.5%22%2C%22text%22%3A%22Planificaci%F3n%20detallada%20y%20guion%20coherente%20y%20s%F3lido.%22%7D%2C%7B%22weight%22%3A%220.3%22%2C%22text%22%3A%22Planificaci%F3n%20clara%2C%20estructura%20l%F3gica.%22%7D%2C%7B%22weight%22%3A%220.15%22%2C%22text%22%3A%22Planificaci%F3n%20b%E1sica%2C%20ideas%20poco%20conectadas.%22%7D%2C%7B%22weight%22%3A%220%22%2C%22text%22%3A%22Sin%20evidencia%20de%20planificaci%F3n.%22%7D%5D%5D%2C%22instructions%22%3A%22%3Cp%3ECon%20esta%20r%FAbrica%2C%20el%20profesor%20va%20a%20evaluar%20tu%20trabajo%20final.%20Estudia%20los%20apartados%20para%20saber%20qu%E9%20se%20te%20pide%20en%20cada%20momento.%3C/p%3E%22%2C%22visible-info%22%3Atrue%2C%22i18n%22%3A%7B%22rubric%22%3A%22R%FAbrica%22%2C%22activity%22%3A%22Actividad%22%2C%22name%22%3A%22Nombre%22%2C%22date%22%3A%22Fecha%22%2C%22score%22%3A%22Puntuaci%F3n%22%2C%22notes%22%3A%22Notas%22%2C%22download%22%3A%22Descargar%22%2C%22msgDelete%22%3A%22%BFSeguro%20que%20desea%20borrar%20todos%20los%20campos%20del%20formulario%3F%22%2C%22reset%22%3A%22Reiniciar%22%2C%22print%22%3A%22Imprimir%22%2C%22apply%22%3A%22Aplicar%22%2C%22newWindow%22%3A%22Ventana%20nueva%22%7D%7D</div><ul class="exe-rubrics-strings"><li class="rubric">Rúbrica</li><li class="activity">Actividad</li><li class="name">Nombre</li><li class="date">Fecha</li><li class="score">Puntuación</li><li class="notes">Notas</li><li class="download">Descargar</li><li class="msgDelete">¿Seguro que desea borrar todos los campos del formulario?</li><li class="reset">Reiniciar</li><li class="print">Imprimir</li><li class="apply">Aplicar</li><li class="newWindow">Ventana nueva</li></ul></div><div class="exe-rubrics-richtext-data sr-av"><span class="exe-rubrics-instructions-data">%3Cp%3ECon%20esta%20r%FAbrica%2C%20el%20profesor%20va%20a%20evaluar%20tu%20trabajo%20final.%20Estudia%20los%20apartados%20para%20saber%20qu%E9%20se%20te%20pide%20en%20cada%20momento.%3C/p%3E</span><span class="exe-rubrics-text-after-data"></span></div></div>]]></htmlView>
          <jsonProperties></jsonProperties>
          <odeComponentsOrder>0</odeComponentsOrder>
          <odeComponentsProperties>
          </odeComponentsProperties>
        </odeComponent>
      </odeComponents>
    </odePagStructure>
  </odePagStructures>
</odeNavStructure>
<odeNavStructure>
  <odePageId>page-1776615301521-akqbkkfa6</odePageId>
  <odeParentPageId></odeParentPageId>
  <pageName>Créditos</pageName>
  <odeNavStructureOrder>3</odeNavStructureOrder>
  <odeNavStructureProperties>
    <odeNavStructureProperty>
      <key>titlePage</key>
      <value>Créditos</value>
    </odeNavStructureProperty>
    <odeNavStructureProperty>
      <key>titleNode</key>
      <value>Créditos</value>
    </odeNavStructureProperty>
  </odeNavStructureProperties>
  <odePagStructures>
    <odePagStructure>
      <odePageId>page-1776615301521-akqbkkfa6</odePageId>
      <odeBlockId>block-1776615521077-k1y4yn3tv</odeBlockId>
      <blockName>Descargar el archivo fuente</blockName>
      <iconName></iconName>
      <odePagStructureOrder>1</odePagStructureOrder>
      <odePagStructureProperties>
        <odePagStructureProperty>
          <key>visibility</key>
          <value>true</value>
        </odePagStructureProperty>
        <odePagStructureProperty>
          <key>teacherOnly</key>
          <value>false</value>
        </odePagStructureProperty>
        <odePagStructureProperty>
          <key>allowToggle</key>
          <value>true</value>
        </odePagStructureProperty>
        <odePagStructureProperty>
          <key>minimized</key>
          <value>false</value>
        </odePagStructureProperty>
        <odePagStructureProperty>
          <key>cssClass</key>
          <value></value>
        </odePagStructureProperty>
      </odePagStructureProperties>
      <odeComponents>
        <odeComponent>
          <odePageId>page-1776615301521-akqbkkfa6</odePageId>
          <odeBlockId>block-1776615521077-k1y4yn3tv</odeBlockId>
          <odeIdeviceId>idevice-1776615521074-ao20s3igf</odeIdeviceId>
          <odeIdeviceTypeName>download-source-file</odeIdeviceTypeName>
          <htmlView><![CDATA[<div class="exe-download-package-instructions"><table class="exe-table exe-package-info"><caption>Información general sobre este recurso educativo</caption>
<tbody>
<tr>
<th>Título</th>
<td class="mceNonEditable exe-prop-locked"><span class="exe-prop-title">Into the unknown</span></td>
</tr>
<tr>
<th>Descripción</th>
<td class="mceNonEditable exe-prop-locked"><span class="exe-prop-description">Este producto está hecho para el curso de B2 de CDD.</span></td>
</tr>
<tr>
<th>Autoría</th>
<td class="mceNonEditable exe-prop-locked"><span class="exe-prop-author">Paula Castillo Martín</span></td>
</tr>
<tr>
<th>Licencia</th>
<td class="mceNonEditable exe-prop-locked"><span class="exe-prop-license">creative commons: attribution - share alike 4.0</span></td>
</tr>
</tbody>
</table>
<p style="text-align: center;">Este contenido fue creado con <a href="https://exelearning.net/">eXeLearning</a>, el editor libre y de fuente abierta diseñado para crear recursos educativos.</p></div><p class="exe-download-package-link"><a download="exe-package:elp-name" href="exe-package:elp" style="background-color:#107275;color:#ffffff;">Descargar el archivo .elpx</a></p>]]></htmlView>
          <jsonProperties></jsonProperties>
          <odeComponentsOrder>0</odeComponentsOrder>
          <odeComponentsProperties>
          </odeComponentsProperties>
        </odeComponent>
      </odeComponents>
    </odePagStructure>
  </odePagStructures>
</odeNavStructure>
</odeNavStructures>
</ode>